ucdp-0.41.0.dist-info/METADATA
ucdp-0.41.0.dist-info/WHEEL
ucdp-0.41.0.dist-info/entry_points.txt
ucdp-0.41.0.dist-info/licenses/LICENSE
ucdp/__init__.py
ucdp/_castingnamespace.py
ucdp/_cligroup.py
ucdp/_logging.py
ucdp/_modbuilder.py
ucdp/_modloader.py
ucdp/_sliceassign.py
ucdp/assigns.py
ucdp/baseclassinfo.py
ucdp/buildproduct.py
ucdp/cache.py
ucdp/casting.py
ucdp/cli.py
ucdp/cliutil.py
ucdp/clkrel.py
ucdp/clkrelbase.py
ucdp/config.py
ucdp/const.py
ucdp/consts.py
ucdp/create.py
ucdp/define.py
ucdp/dict.py
ucdp/doc.py
ucdp/docutil.py
ucdp/drivers.py
ucdp/examples/bad/glbl_bad_lib/__init__.py
ucdp/examples/bad/glbl_bad_lib/regf.py
ucdp/examples/filelist/filelist_lib/filelist.py
ucdp/examples/filelist/filelist_lib/mod.f
ucdp/examples/param/param_lib/param.py
ucdp/examples/simple/fileliststandard.py
ucdp/examples/simple/glbl_lib/$PRJROOT/uart_lib/uart/rtl/uart_regf.sv
ucdp/examples/simple/glbl_lib/__init__.py
ucdp/examples/simple/glbl_lib/bus.py
ucdp/examples/simple/glbl_lib/clk_gate.py
ucdp/examples/simple/glbl_lib/regf.py
ucdp/examples/simple/glbl_lib/regf_tb.py
ucdp/examples/simple/uart_lib/__init__.py
ucdp/examples/simple/uart_lib/sv.mako
ucdp/examples/simple/uart_lib/uart.py
ucdp/exceptions.py
ucdp/expr.py
ucdp/exprparser.py
ucdp/exprresolver.py
ucdp/filelistparser.py
ucdp/fileset.py
ucdp/finder.py
ucdp/flipflop.py
ucdp/generate.py
ucdp/humannum.py
ucdp/ident.py
ucdp/ifdef.py
ucdp/iterutil.py
ucdp/loader.py
ucdp/logging.py
ucdp/mod.py
ucdp/modbase.py
ucdp/modbasetop.py
ucdp/modconfigurable.py
ucdp/modconfigurabletb.py
ucdp/modcore.py
ucdp/modfilelist.py
ucdp/modgenerictb.py
ucdp/moditer.py
ucdp/modref.py
ucdp/modtailored.py
ucdp/modtb.py
ucdp/modtopref.py
ucdp/modtoprefinfo.py
ucdp/modutil.py
ucdp/mux.py
ucdp/namespace.py
ucdp/nameutil.py
ucdp/note.py
ucdp/object.py
ucdp/orientation.py
ucdp/overview.py
ucdp/param.py
ucdp/pathutil.py
ucdp/routepath.py
ucdp/signal.py
ucdp/slices.py
ucdp/test.py
ucdp/top.py
ucdp/typearray.py
ucdp/typebase.py
ucdp/typebaseenum.py
ucdp/typeclkrst.py
ucdp/typedescriptivestruct.py
ucdp/typeenum.py
ucdp/typefloat.py
ucdp/typehelper.py
ucdp/typescalar.py
ucdp-0.41.0.dist-info/RECORD
