Metadata-Version: 2.1
Name: ucdp
Version: 0.41.0
Summary: Unified Chip Design Platform
Classifier: Programming Language :: Python :: 3
Classifier: Operating System :: OS Independent
Project-URL: Homepage, https://github.com/nbiotcloud/ucdp
Project-URL: Documentation, https://ucdp.readthedocs.io/en/stable/
Project-URL: Bug Tracker, https://github.com/nbiotcloud/ucdp/issues
Requires-Python: <4.0,>=3.10.0
Requires-Dist: anycache>=2.2.0
Requires-Dist: anytree>=2.12.1
Requires-Dist: case-converter>=1.1.0
Requires-Dist: click-bash4-2-completion>=0.1.0
Requires-Dist: click>=8.1.7
Requires-Dist: fuzzywuzzy>=0.18.0
Requires-Dist: humannum>=1.2.0
Requires-Dist: icdutil>=0.3.1
Requires-Dist: makolator>=2.11.0
Requires-Dist: matchor>=0.1.0
Requires-Dist: platformdirs>=4.3.7
Requires-Dist: pydantic>=2.7.0
Requires-Dist: python-Levenshtein>=0.25.1
Requires-Dist: rich>=13.7.1
Requires-Dist: uniquer>=1.0.2
